Metadata-Version: 2.1
Name: btl
Version: 0.9.9
Summary: A FreeCAD addon and a CLI tool to manage tool libraries
Author-email: Samuel <knipknap@gmail.com>
Project-URL: Homepage, https://github.com/knipknap/better-tool-library
Project-URL: Bug Tracker, https://github.com/knipknap/better-tool-library/issues
Classifier: Programming Language :: Python :: 3
Classifier: License :: OSI Approved :: MIT License
Classifier: Operating System :: OS Independent
Requires-Python: >=3.7
License-File: LICENSE
